rid/RingFence.py
rid/__init__.py
Ring_Fence-0.0.1.dist-info/METADATA
Ring_Fence-0.0.1.dist-info/WHEEL
Ring_Fence-0.0.1.dist-info/top_level.txt
Ring_Fence-0.0.1.dist-info/RECORD
