Metadata-Version: 2.1
Name: Ring-Fence
Version: 0.0.1
Summary: A package to create ring fence for data objects
Home-page: https://github.com/pypa/sampleproject
Author: Anuneet, Hamzah, Himanshu
Author-email: hamzah18051@example.com
License: UNKNOWN
Platform: UNKNOWN
Classifier: Programming Language :: Python :: 3
Classifier: License :: OSI Approved :: MIT License
Classifier: Operating System :: OS Independent
Requires-Python: >=3.6
